quick_preprocessing/__init__.py
quick_preprocessing/logger.py
quick_preprocessing/manual_exception.py
quick_preprocessing/preprocessing.py
quick_preprocessing-0.0.8.dist-info/LICENSE
quick_preprocessing-0.0.8.dist-info/METADATA
quick_preprocessing-0.0.8.dist-info/WHEEL
quick_preprocessing-0.0.8.dist-info/top_level.txt
quick_preprocessing-0.0.8.dist-info/RECORD
